dicgram/__init__.py
dicgram/cliente.py
dicgram/decorators.py
dicgram/mensagem.py
dicgram/metodos.py
dicgram-2.1.2.dist-info/LICENSE
dicgram-2.1.2.dist-info/METADATA
dicgram-2.1.2.dist-info/WHEEL
dicgram-2.1.2.dist-info/top_level.txt
dicgram-2.1.2.dist-info/RECORD
