Metadata-Version: 2.1
Name: dicgram
Version: 2.1.2
Summary: Framework para criar bots do Telegram
Home-page: https://github.com/marcellobatiista/dicgram
Author: Marcelo Batista
Author-email: batista.marcelo34@gmail.com
License: MIT
Keywords: telegram chat messenger api client library python
Platform: UNKNOWN
Requires-Python: >=3.7
Requires-Dist: requests
Requires-Dist: beautifulsoup4
Requires-Dist: setuptools
Requires-Dist: flask
